tests/__init__.py
tests/test_bc.py
tests/test_ppo.py
tests/test_unityagents.py
tests/test_unitytrainers.py
unityagents/__init__.py
unityagents/brain.py
unityagents/curriculum.py
unityagents/environment.py
unityagents/exception.py
unityagents-0.3.0.dist-info/DESCRIPTION.rst
unityagents-0.3.0.dist-info/METADATA
unityagents-0.3.0.dist-info/RECORD
unityagents-0.3.0.dist-info/WHEEL
unityagents-0.3.0.dist-info/metadata.json
unityagents-0.3.0.dist-info/top_level.txt
unitytrainers/__init__.py
unitytrainers/buffer.py
unitytrainers/models.py
unitytrainers/trainer.py
unitytrainers/trainer_controller.py
unitytrainers/bc/__init__.py
unitytrainers/bc/models.py
unitytrainers/bc/trainer.py
unitytrainers/ppo/__init__.py
unitytrainers/ppo/models.py
unitytrainers/ppo/trainer.py
