Metadata-Version: 2.0
Name: unityagents
Version: 0.3.0
Summary: Unity Machine Learning Agents
Home-page: https://github.com/Unity-Technologies/ml-agents
Author: Unity Technologies
Author-email: ML-Agents@unity3d.com
License: Apache License 2.0
Platform: UNKNOWN
Requires-Dist: Pillow (>=4.2.1)
Requires-Dist: docopt
Requires-Dist: jupyter
Requires-Dist: matplotlib
Requires-Dist: numpy (>=1.11.0)
Requires-Dist: pytest (>=3.2.2)
Requires-Dist: pyyaml
Requires-Dist: tensorflow (==1.4.0)
